scope_profiler/__init__.py
scope_profiler/h5reader.py
scope_profiler/mpi_region.py
scope_profiler/plotting_scripts.py
scope_profiler/post_processing.py
scope_profiler/profile_config.py
scope_profiler/profile_manager.py
scope_profiler/region.py
scope_profiler/region_profiler.py
scope_profiler/tests/__init__.py
scope_profiler/tests/examples.py
scope_profiler/tests/examples_pylikwid.py
scope_profiler/tests/pylikwid_readme.py
scope_profiler/tests/test_app.py
scope_profiler/tests/test_mpi.py
scope_profiler/tests/test_overhead.py
scope_profiler/tests/test_readme.py
scope_profiler-0.1.7.dist-info/METADATA
scope_profiler-0.1.7.dist-info/WHEEL
scope_profiler-0.1.7.dist-info/entry_points.txt
scope_profiler-0.1.7.dist-info/top_level.txt
scope_profiler-0.1.7.dist-info/RECORD
