Metadata-Version: 2.4
Name: scope-profiler
Version: 0.1.7
Summary: Profile code regions in python, optionally with LIKWID markers.
Author: Max
Project-URL: Source, https://github.com/max-models/scope-profiler
Keywords: python
Classifier: Development Status :: 3 - Alpha
Classifier: Programming Language :: Python :: 3 :: Only
Classifier: Programming Language :: Python :: 3.8
Classifier: Programming Language :: Python :: 3.9
Classifier: Programming Language :: Python :: 3.10
Classifier: Programming Language :: Python :: 3.11
Classifier: Programming Language :: Python :: 3.12
Classifier: Programming Language :: Python :: 3.13
Classifier: Programming Language :: Python :: 3.14
Requires-Python: >=3.8
Requires-Dist: h5py
Requires-Dist: numpy
Provides-Extra: mpi
Requires-Dist: mpi4py; extra == "mpi"
Provides-Extra: dev
Requires-Dist: black[jupyter]; extra == "dev"
Requires-Dist: isort; extra == "dev"
Requires-Dist: ruff; extra == "dev"
Requires-Dist: matplotlib; extra == "dev"
Requires-Dist: scope-profiler[docs,mpi,test]; extra == "dev"
Provides-Extra: docs
Requires-Dist: ipykernel; extra == "docs"
Requires-Dist: jupyterlab; extra == "docs"
Requires-Dist: myst-parser; extra == "docs"
Requires-Dist: nbconvert; extra == "docs"
Requires-Dist: nbsphinx; extra == "docs"
Requires-Dist: pre-commit; extra == "docs"
Requires-Dist: pyproject-fmt; extra == "docs"
Requires-Dist: sphinx; extra == "docs"
Requires-Dist: sphinx-book-theme; extra == "docs"
Provides-Extra: test
Requires-Dist: coverage; extra == "test"
Requires-Dist: pytest; extra == "test"
